strata/__init__.py
strata/licenses/cli11-license.txt
strata/licenses/rapidjson-license.txt
strata_cli-0.3.0.dist-info/licenses/LICENSE.txt
strata_cli-0.3.0.dist-info/METADATA
strata_cli-0.3.0.dist-info/WHEEL
strata_cli-0.3.0.dist-info/entry_points.txt
strata_cli-0.3.0.dist-info/top_level.txt
strata_cli-0.3.0.dist-info/RECORD
