Metadata-Version: 2.4
Name: strata-cli
Version: 0.3.0
Summary: The easy way to ship Stan models
Author-email: Andrew Kane <andrew@ankane.org>
License: BSD-3-Clause
Project-URL: Homepage, https://github.com/ankane/strata
Requires-Python: >=3.9
License-File: LICENSE.txt
Dynamic: license-file
